rsl_rl/__init__.py
rsl_rl/algorithms/__init__.py
rsl_rl/algorithms/distillation.py
rsl_rl/algorithms/ppo.py
rsl_rl/env/__init__.py
rsl_rl/env/vec_env.py
rsl_rl/modules/__init__.py
rsl_rl/modules/actor_critic.py
rsl_rl/modules/actor_critic_recurrent.py
rsl_rl/modules/rnd.py
rsl_rl/modules/student_teacher.py
rsl_rl/modules/student_teacher_recurrent.py
rsl_rl/modules/symmetry.py
rsl_rl/networks/__init__.py
rsl_rl/networks/memory.py
rsl_rl/networks/mlp.py
rsl_rl/networks/normalization.py
rsl_rl/runners/__init__.py
rsl_rl/runners/distillation_runner.py
rsl_rl/runners/on_policy_runner.py
rsl_rl/storage/__init__.py
rsl_rl/storage/rollout_storage.py
rsl_rl/utils/__init__.py
rsl_rl/utils/neptune_utils.py
rsl_rl/utils/utils.py
rsl_rl/utils/wandb_utils.py
rsl_rl_lib-3.1.3.dist-info/licenses/LICENSE
rsl_rl_lib-3.1.3.dist-info/METADATA
rsl_rl_lib-3.1.3.dist-info/WHEEL
rsl_rl_lib-3.1.3.dist-info/top_level.txt
rsl_rl_lib-3.1.3.dist-info/RECORD
